{
  "generated_at": "2026-02-15T04:31:08.220499+08:00",
  "results": [
    {
      "symbol": "BTC-USDT",
      "source": "Crypto",
      "chart_url": "https://www.tradingview.com/chart/?symbol=OKX:BTCUSDT",
      "timestamp": "2026-02-15T04:28:45.458142+08:00",
      "has_signal": true,
      "daily": {
        "signals": [
          "三役逆轉"
        ],
        "trend": "趨勢不明確",
        "recommendation": "做空",
        "price": 69905.8,
        "tenkan_sen": 68704.05,
        "kijun_sen": 75611.0,
        "cloud_top": 93092.2,
        "cloud_bottom": 90879.4,
        "senkou_span_a": 93092.2,
        "senkou_span_b": 90879.4
      },
      "h4": {
        "signals": [
          "三役好轉"
        ],
        "trend": "趨勢不明確",
        "recommendation": "做多",
        "price": 69905.8,
        "tenkan_sen": 68721.70000000001,
        "kijun_sen": 67848.45,
        "cloud_top": 69667.75,
        "cloud_bottom": 69008.70000000001,
        "senkou_span_a": 69008.70000000001,
        "senkou_span_b": 69667.75
      },
      "combined_recommendation": "觀望等待",
      "combined_explanation": "逆勢反彈風險高，不建議追多",
      "ai_advice": "根據一目均衡表數據，建議觀望等待。日線和4小時線的趨勢強度不明確，系統判定綜合建議也為觀望等待。\n\n1. **操作建議**：觀望等待\n2. **進場價位**：無\n3. **停損位置**：無\n4. **目標價位**：無\n5. **風險提醒**：注意價格波動風險，待趨勢明確後再進行交易。",
      "ai_provider": "GROQ",
      "ai_model": "llama-3.3-70b-versatile"
    },
    {
      "symbol": "ETH-USDT",
      "source": "Crypto",
      "chart_url": "https://www.tradingview.com/chart/?symbol=OKX:ETHUSDT",
      "timestamp": "2026-02-15T04:28:45.486111+08:00",
      "has_signal": true,
      "daily": {
        "signals": [
          "三役逆轉"
        ],
        "trend": "趨勢不明確",
        "recommendation": "做空",
        "price": 2087.59,
        "tenkan_sen": 2024.43,
        "kijun_sen": 2406.75,
        "cloud_top": 3173.2974999999997,
        "cloud_bottom": 3083.715,
        "senkou_span_a": 3173.2974999999997,
        "senkou_span_b": 3083.715
      },
      "h4": {
        "signals": [
          "三役好轉"
        ],
        "trend": "趨勢不明確",
        "recommendation": "做多",
        "price": 2087.59,
        "tenkan_sen": 2030.34,
        "kijun_sen": 2002.175,
        "cloud_top": 2070.3900000000003,
        "cloud_bottom": 2038.83,
        "senkou_span_a": 2038.83,
        "senkou_span_b": 2070.3900000000003
      },
      "combined_recommendation": "觀望等待",
      "combined_explanation": "逆勢反彈風險高，不建議追多",
      "ai_advice": "根據一目均衡表數據，建議：\n1. **操作建議**：觀望等待，因為日線和4小時線的信號相互矛盾。\n2. **進場價位**：無建議，因為觀望等待。\n3. **停損位置**：無建議，因為觀望等待。\n4. **目標價位**：無建議，因為觀望等待。\n5. **風險提醒**：注意趨勢不明確和信號相互矛盾，避免盲目交易。",
      "ai_provider": "GROQ",
      "ai_model": "llama-3.3-70b-versatile"
    },
    {
      "symbol": "BNB-USDT",
      "source": "Crypto",
      "chart_url": "https://www.tradingview.com/chart/?symbol=OKX:BNBUSDT",
      "timestamp": "2026-02-15T04:28:45.318562+08:00",
      "has_signal": true,
      "daily": {
        "signals": [
          "三役逆轉"
        ],
        "trend": "趨勢不明確",
        "recommendation": "做空",
        "price": 631.9,
        "tenkan_sen": 628.45,
        "kijun_sen": 739.75,
        "cloud_top": 908.5250000000001,
        "cloud_bottom": 880.65,
        "senkou_span_a": 908.5250000000001,
        "senkou_span_b": 880.65
      },
      "h4": {
        "signals": [],
        "trend": "趨勢不明確",
        "recommendation": "觀望",
        "price": 631.9,
        "tenkan_sen": 616.5,
        "kijun_sen": 612.4,
        "cloud_top": 676.6,
        "cloud_bottom": 635.6,
        "senkou_span_a": 635.6,
        "senkou_span_b": 676.6
      },
      "combined_recommendation": "偏空操作",
      "combined_explanation": "日線空頭，等待4H確認進場點",
      "ai_advice": "根據一目均衡表數據，提供以下建議：\n\n1. **操作建議**：做空\n2. **進場價位**：630-635區間\n3. **停損位置**：設於雲層上緣，約676.6000\n4. **目標價位**：約610-600區間\n5. **風險提醒**：注意日線基準線739.7500的反彈風險，及雲層範圍的支撐作用。",
      "ai_provider": "GROQ",
      "ai_model": "llama-3.3-70b-versatile"
    },
    {
      "symbol": "SOL-USDT",
      "source": "Crypto",
      "chart_url": "https://www.tradingview.com/chart/?symbol=OKX:SOLUSDT",
      "timestamp": "2026-02-15T04:28:45.435445+08:00",
      "has_signal": true,
      "daily": {
        "signals": [
          "三役逆轉"
        ],
        "trend": "趨勢不明確",
        "recommendation": "做空",
        "price": 87.98,
        "tenkan_sen": 83.205,
        "kijun_sen": 99.795,
        "cloud_top": 135.97750000000002,
        "cloud_bottom": 132.78,
        "senkou_span_a": 135.97750000000002,
        "senkou_span_b": 132.78
      },
      "h4": {
        "signals": [
          "三役好轉"
        ],
        "trend": "趨勢不明確",
        "recommendation": "做多",
        "price": 87.98,
        "tenkan_sen": 84.09,
        "kijun_sen": 82.515,
        "cloud_top": 86.78,
        "cloud_bottom": 85.02,
        "senkou_span_a": 85.02,
        "senkou_span_b": 86.78
      },
      "combined_recommendation": "觀望等待",
      "combined_explanation": "逆勢反彈風險高，不建議追多",
      "ai_advice": "根據提供的數據，系統判定綜合建議為觀望等待，但考慮到4小時線的單週期建議為做多，且雲層範圍較窄，表明市場可能出現反彈。\n\n1. **操作建議**：做多\n2. **進場價位**：85.0 ~ 87.0\n3. **停損位置**：82.0\n4. **目標價位**：92.0\n5. **風險提醒**：注意日線趨勢不明確，做空訊號可能導致下跌。",
      "ai_provider": "GROQ",
      "ai_model": "llama-3.3-70b-versatile"
    },
    {
      "symbol": "XRP-USDT",
      "source": "Crypto",
      "chart_url": "https://www.tradingview.com/chart/?symbol=OKX:XRPUSDT",
      "timestamp": "2026-02-15T04:28:45.519246+08:00",
      "has_signal": true,
      "daily": {
        "signals": [
          "三役逆轉"
        ],
        "trend": "趨勢不明確",
        "recommendation": "做空",
        "price": 1.4962,
        "tenkan_sen": 1.4386999999999999,
        "kijun_sen": 1.5544,
        "cloud_top": 2.0942,
        "cloud_bottom": 2.0667999999999997,
        "senkou_span_a": 2.0667999999999997,
        "senkou_span_b": 2.0942
      },
      "h4": {
        "signals": [
          "三役好轉"
        ],
        "trend": "強勢上升趨勢",
        "recommendation": "做多",
        "price": 1.4961,
        "tenkan_sen": 1.4341,
        "kijun_sen": 1.4253,
        "cloud_top": 1.41655,
        "cloud_bottom": 1.38795,
        "senkou_span_a": 1.41655,
        "senkou_span_b": 1.38795
      },
      "combined_recommendation": "觀望等待",
      "combined_explanation": "逆勢反彈風險高，不建議追多",
      "ai_advice": "根據一目均衡表數據，系統判定綜合建議為觀望等待，但考慮到4小時線的強勢上升趨勢和三役好轉訊號，建議**做多**。\n\n- **進場價位**：1.48 ~ 1.50\n- **停損位置**：1.42（基於4小時線基準線）\n- **目標價位**：1.55（基於日線基準線）\n- **風險提醒**：注意日線趨勢不明確和三役逆轉的反彈風險。",
      "ai_provider": "GROQ",
      "ai_model": "llama-3.3-70b-versatile"
    },
    {
      "symbol": "ADA-USDT",
      "source": "Crypto",
      "chart_url": "https://www.tradingview.com/chart/?symbol=OKX:ADAUSDT",
      "timestamp": "2026-02-15T04:28:45.350893+08:00",
      "has_signal": true,
      "daily": {
        "signals": [
          "三役逆轉"
        ],
        "trend": "趨勢不明確",
        "recommendation": "做空",
        "price": 0.2977,
        "tenkan_sen": 0.27535,
        "kijun_sen": 0.2972,
        "cloud_top": 0.4065,
        "cloud_bottom": 0.383725,
        "senkou_span_a": 0.383725,
        "senkou_span_b": 0.4065
      },
      "h4": {
        "signals": [
          "三役好轉"
        ],
        "trend": "強勢上升趨勢",
        "recommendation": "做多",
        "price": 0.2977,
        "tenkan_sen": 0.2812,
        "kijun_sen": 0.27535,
        "cloud_top": 0.266575,
        "cloud_bottom": 0.2626,
        "senkou_span_a": 0.266575,
        "senkou_span_b": 0.2626
      },
      "combined_recommendation": "觀望等待",
      "combined_explanation": "逆勢反彈風險高，不建議追多",
      "ai_advice": "根據一目均衡表數據，日線和4小時線出現矛盾，建議**觀望等待**。\n- **進場價位**：無明確建議\n- **停損位置**：無明確建議\n- **目標價位**：無明確建議\n- **風險提醒**：趨勢不明確，需謹慎交易，等待更明確的信號出現。",
      "ai_provider": "GROQ",
      "ai_model": "llama-3.3-70b-versatile"
    },
    {
      "symbol": "DOGE-USDT",
      "source": "Crypto",
      "chart_url": "https://www.tradingview.com/chart/?symbol=OKX:DOGEUSDT",
      "timestamp": "2026-02-15T04:28:45.415201+08:00",
      "has_signal": true,
      "daily": {
        "signals": [
          "三役逆轉"
        ],
        "trend": "趨勢不明確",
        "recommendation": "做空",
        "price": 0.10879,
        "tenkan_sen": 0.09861,
        "kijun_sen": 0.104405,
        "cloud_top": 0.136235,
        "cloud_bottom": 0.13581,
        "senkou_span_a": 0.13581,
        "senkou_span_b": 0.136235
      },
      "h4": {
        "signals": [
          "三役好轉"
        ],
        "trend": "強勢上升趨勢",
        "recommendation": "做多",
        "price": 0.10884,
        "tenkan_sen": 0.101135,
        "kijun_sen": 0.09861,
        "cloud_top": 0.09529750000000001,
        "cloud_bottom": 0.09528,
        "senkou_span_a": 0.09529750000000001,
        "senkou_span_b": 0.09528
      },
      "combined_recommendation": "觀望等待",
      "combined_explanation": "逆勢反彈風險高，不建議追多",
      "ai_advice": "根據一目均衡表數據：\n1. **操作建議**：觀望等待，避免進場。\n2. **進場價位**：無建議進場。\n3. **停損位置**：無。\n4. **目標價位**：無。\n5. **風險提醒**：日線和4小時線訊號不一致，趨勢不明確，建議等待確定趨勢後再進場。",
      "ai_provider": "GROQ",
      "ai_model": "llama-3.3-70b-versatile"
    },
    {
      "symbol": "AVAX-USDT",
      "source": "Crypto",
      "chart_url": "https://www.tradingview.com/chart/?symbol=OKX:AVAXUSDT",
      "timestamp": "2026-02-15T04:28:45.255313+08:00",
      "has_signal": true,
      "daily": {
        "signals": [
          "三役逆轉"
        ],
        "trend": "趨勢不明確",
        "recommendation": "做空",
        "price": 9.59,
        "tenkan_sen": 9.0475,
        "kijun_sen": 10.135,
        "cloud_top": 13.4985,
        "cloud_bottom": 13.175,
        "senkou_span_a": 13.4985,
        "senkou_span_b": 13.175
      },
      "h4": {
        "signals": [
          "三役好轉"
        ],
        "trend": "趨勢不明確",
        "recommendation": "做多",
        "price": 9.59,
        "tenkan_sen": 9.2445,
        "kijun_sen": 9.0475,
        "cloud_top": 8.9465,
        "cloud_bottom": 8.92625,
        "senkou_span_a": 8.92625,
        "senkou_span_b": 8.9465
      },
      "combined_recommendation": "觀望等待",
      "combined_explanation": "逆勢反彈風險高，不建議追多",
      "ai_advice": "根據一目均衡表數據，提供以下交易建議：\n\n1. **操作建議**：觀望等待，短期內不建議做多或做空。\n2. **進場價位**：無。\n3. **停損位置**：無。\n4. **目標價位**：無。\n5. **風險提醒**：日線和4小時線的訊號不一致，趨勢不明確，建議等待趨勢明朗後再進行交易。",
      "ai_provider": "GROQ",
      "ai_model": "llama-3.3-70b-versatile"
    },
    {
      "symbol": "DOT-USDT",
      "source": "Crypto",
      "chart_url": "https://www.tradingview.com/chart/?symbol=OKX:DOTUSDT",
      "timestamp": "2026-02-15T04:28:45.469104+08:00",
      "has_signal": true,
      "daily": {
        "signals": [
          "三役逆轉"
        ],
        "trend": "趨勢不明確",
        "recommendation": "做空",
        "price": 1.422,
        "tenkan_sen": 1.3285,
        "kijun_sen": 1.5510000000000002,
        "cloud_top": 2.0462499999999997,
        "cloud_bottom": 2.026,
        "senkou_span_a": 2.0462499999999997,
        "senkou_span_b": 2.026
      },
      "h4": {
        "signals": [
          "三役好轉"
        ],
        "trend": "趨勢不明確",
        "recommendation": "做多",
        "price": 1.422,
        "tenkan_sen": 1.3515,
        "kijun_sen": 1.3285,
        "cloud_top": 1.339,
        "cloud_bottom": 1.3205,
        "senkou_span_a": 1.3205,
        "senkou_span_b": 1.339
      },
      "combined_recommendation": "觀望等待",
      "combined_explanation": "逆勢反彈風險高，不建議追多",
      "ai_advice": "根據一目均衡表數據，提供以下建議：\n\n1. **操作建議**：觀望等待，因為日線和4小時線的建議相反。\n2. **進場價位**：無建議，因為觀望等待。\n3. **停損位置**：無建議，因為觀望等待。\n4. **目標價位**：無建議，因為觀望等待。\n5. **風險提醒**：注意日線和4小時線的趨勢不明確，建議等待更明確的信號。",
      "ai_provider": "GROQ",
      "ai_model": "llama-3.3-70b-versatile"
    },
    {
      "symbol": "POL-USDT",
      "source": "Crypto",
      "chart_url": "https://www.tradingview.com/chart/?symbol=OKX:POLUSDT",
      "timestamp": "2026-02-15T04:28:45.397701+08:00",
      "has_signal": true,
      "daily": {
        "signals": [
          "三役逆轉"
        ],
        "trend": "趨勢不明確",
        "recommendation": "做空",
        "price": 0.11059,
        "tenkan_sen": 0.10281,
        "kijun_sen": 0.1124,
        "cloud_top": 0.145675,
        "cloud_bottom": 0.14265,
        "senkou_span_a": 0.145675,
        "senkou_span_b": 0.14265
      },
      "h4": {
        "signals": [
          "三役好轉"
        ],
        "trend": "趨勢不明確",
        "recommendation": "做多",
        "price": 0.11059,
        "tenkan_sen": 0.106465,
        "kijun_sen": 0.10281,
        "cloud_top": 0.1013,
        "cloud_bottom": 0.0947,
        "senkou_span_a": 0.0947,
        "senkou_span_b": 0.1013
      },
      "combined_recommendation": "觀望等待",
      "combined_explanation": "逆勢反彈風險高，不建議追多",
      "ai_advice": "根據一目均衡表數據，提供以下建議：\n\n1. **操作建議**：觀望等待，因為日線和4小時線的趨勢強度不明確，單週期建議相互衝突。\n2. **進場價位**：無建議，因為觀望等待。\n3. **停損位置**：無建議，因為觀望等待。\n4. **目標價位**：無建議，因為觀望等待。\n5. **風險提醒**：注意價格可能的劇烈波動，日線和4小時線的衝突可能引發市場不確定性。",
      "ai_provider": "GROQ",
      "ai_model": "llama-3.3-70b-versatile"
    },
    {
      "symbol": "LINK-USDT",
      "source": "Crypto",
      "chart_url": "https://www.tradingview.com/chart/?symbol=OKX:LINKUSDT",
      "timestamp": "2026-02-15T04:28:45.918154+08:00",
      "has_signal": true,
      "daily": {
        "signals": [
          "三役逆轉"
        ],
        "trend": "趨勢不明確",
        "recommendation": "做空",
        "price": 9.13,
        "tenkan_sen": 8.659500000000001,
        "kijun_sen": 9.915,
        "cloud_top": 13.3735,
        "cloud_bottom": 13.28,
        "senkou_span_a": 13.28,
        "senkou_span_b": 13.3735
      },
      "h4": {
        "signals": [
          "三役好轉"
        ],
        "trend": "強勢上升趨勢",
        "recommendation": "做多",
        "price": 9.13,
        "tenkan_sen": 8.797,
        "kijun_sen": 8.659500000000001,
        "cloud_top": 8.628,
        "cloud_bottom": 8.593,
        "senkou_span_a": 8.628,
        "senkou_span_b": 8.593
      },
      "combined_recommendation": "觀望等待",
      "combined_explanation": "逆勢反彈風險高，不建議追多",
      "ai_advice": "根據一目均衡表數據，建議觀望等待，不立即進行交易。日線和4小時線的信號不一致，日線建議做空，而4小時線建議做多，表明市場趨勢不明確。\n\n- **操作建議**：觀望等待\n- **進場價位**：無\n- **停損位置**：無\n- **目標價位**：無\n- **風險提醒**：市場趨勢不明確，等待清晰的趨勢信號出現後再進行交易。",
      "ai_provider": "GROQ",
      "ai_model": "llama-3.3-70b-versatile"
    },
    {
      "symbol": "UNI-USDT",
      "source": "Crypto",
      "chart_url": "https://www.tradingview.com/chart/?symbol=OKX:UNIUSDT",
      "timestamp": "2026-02-15T04:28:46.047539+08:00",
      "has_signal": true,
      "daily": {
        "signals": [
          "三役逆轉"
        ],
        "trend": "強勢下降趨勢",
        "recommendation": "做空",
        "price": 3.661,
        "tenkan_sen": 3.8465,
        "kijun_sen": 3.9545,
        "cloud_top": 5.584,
        "cloud_bottom": 5.404999999999999,
        "senkou_span_a": 5.404999999999999,
        "senkou_span_b": 5.584
      },
      "h4": {
        "signals": [],
        "trend": "趨勢不明確",
        "recommendation": "觀望",
        "price": 3.661,
        "tenkan_sen": 3.5205,
        "kijun_sen": 3.8465,
        "cloud_top": 3.435,
        "cloud_bottom": 3.4255,
        "senkou_span_a": 3.4255,
        "senkou_span_b": 3.435
      },
      "combined_recommendation": "偏空操作",
      "combined_explanation": "日線空頭，等待4H確認進場點",
      "ai_advice": "根據一目均衡表數據，對UNI-USDT的操作建議如下：\n\n1. **操作建議**：做空\n2. **進場價位**：3.65 ~ 3.70\n3. **停損位置**：3.85（基準線）\n4. **目標價位**：3.45（雲層下緣）\n5. **風險提醒**：注意趨勢強度的變化，若轉換線與基準線交叉，可能會出現反彈。",
      "ai_provider": "GROQ",
      "ai_model": "llama-3.3-70b-versatile"
    },
    {
      "symbol": "ATOM-USDT",
      "source": "Crypto",
      "chart_url": "https://www.tradingview.com/chart/?symbol=OKX:ATOMUSDT",
      "timestamp": "2026-02-15T04:28:46.003674+08:00",
      "has_signal": true,
      "daily": {
        "signals": [
          "三役逆轉"
        ],
        "trend": "趨勢不明確",
        "recommendation": "做空",
        "price": 2.204,
        "tenkan_sen": 2.047,
        "kijun_sen": 2.0525,
        "cloud_top": 2.38375,
        "cloud_bottom": 2.2655,
        "senkou_span_a": 2.38375,
        "senkou_span_b": 2.2655
      },
      "h4": {
        "signals": [
          "三役好轉"
        ],
        "trend": "強勢上升趨勢",
        "recommendation": "做多",
        "price": 2.204,
        "tenkan_sen": 2.112,
        "kijun_sen": 2.047,
        "cloud_top": 1.9315,
        "cloud_bottom": 1.88,
        "senkou_span_a": 1.9315,
        "senkou_span_b": 1.88
      },
      "combined_recommendation": "觀望等待",
      "combined_explanation": "逆勢反彈風險高，不建議追多",
      "ai_advice": "根據一目均衡表數據，日線和4小時線出現分歧，系統判定綜合建議為觀望等待。考慮到趨勢強度和偵測訊號，建議觀望等待，待進一步確認趨勢。\n\n* **操作建議**：觀望等待\n* **進場價位**：無建議\n* **停損位置**：無建議\n* **目標價位**：無建議\n* **風險提醒**：注意趨勢不明確和分時框架分歧，避免盲目交易。",
      "ai_provider": "GROQ",
      "ai_model": "llama-3.3-70b-versatile"
    },
    {
      "symbol": "LTC-USDT",
      "source": "Crypto",
      "chart_url": "https://www.tradingview.com/chart/?symbol=OKX:LTCUSDT",
      "timestamp": "2026-02-15T04:28:46.136914+08:00",
      "has_signal": true,
      "daily": {
        "signals": [
          "三役逆轉"
        ],
        "trend": "趨勢不明確",
        "recommendation": "做空",
        "price": 56.25,
        "tenkan_sen": 53.825,
        "kijun_sen": 57.755,
        "cloud_top": 76.44,
        "cloud_bottom": 74.1825,
        "senkou_span_a": 74.1825,
        "senkou_span_b": 76.44
      },
      "h4": {
        "signals": [
          "三役好轉"
        ],
        "trend": "強勢上升趨勢",
        "recommendation": "做多",
        "price": 56.25,
        "tenkan_sen": 54.8,
        "kijun_sen": 53.825,
        "cloud_top": 53.622499999999995,
        "cloud_bottom": 53.225,
        "senkou_span_a": 53.622499999999995,
        "senkou_span_b": 53.225
      },
      "combined_recommendation": "觀望等待",
      "combined_explanation": "逆勢反彈風險高，不建議追多",
      "ai_advice": "根據提供的數據，建議觀望等待。日線圖顯示趨勢不明確，單週期建議做空，而4小時線圖顯示強勢上升趨勢，單週期建議做多，兩者相互矛盾，因此不宜進行交易。需要觀察市場走勢，等待明確的趨勢信號。",
      "ai_provider": "GROQ",
      "ai_model": "llama-3.3-70b-versatile"
    },
    {
      "symbol": "ETC-USDT",
      "source": "Crypto",
      "chart_url": "https://www.tradingview.com/chart/?symbol=OKX:ETCUSDT",
      "timestamp": "2026-02-15T04:28:46.106915+08:00",
      "has_signal": true,
      "daily": {
        "signals": [
          "三役逆轉"
        ],
        "trend": "趨勢不明確",
        "recommendation": "做空",
        "price": 8.98,
        "tenkan_sen": 8.485,
        "kijun_sen": 9.530000000000001,
        "cloud_top": 12.71,
        "cloud_bottom": 12.2925,
        "senkou_span_a": 12.2925,
        "senkou_span_b": 12.71
      },
      "h4": {
        "signals": [
          "三役好轉"
        ],
        "trend": "趨勢不明確",
        "recommendation": "做多",
        "price": 8.98,
        "tenkan_sen": 8.64,
        "kijun_sen": 8.485,
        "cloud_top": 8.545,
        "cloud_bottom": 8.5025,
        "senkou_span_a": 8.5025,
        "senkou_span_b": 8.545
      },
      "combined_recommendation": "觀望等待",
      "combined_explanation": "逆勢反彈風險高，不建議追多",
      "ai_advice": "根據一目均衡表數據，提供以下建議：\n\n1. **操作建議**：觀望等待，日線做空信號與4小時線做多信號衝突。\n2. **進場價位**：無建議，等待趨勢明確。\n3. **停損位置**：無建議，觀望等待。\n4. **目標價位**：無建議，觀望等待。\n5. **風險提醒**：注意日線與4小時線信號衝突的風險，避免盲目交易。",
      "ai_provider": "GROQ",
      "ai_model": "llama-3.3-70b-versatile"
    },
    {
      "symbol": "XLM-USDT",
      "source": "Crypto",
      "chart_url": "https://www.tradingview.com/chart/?symbol=OKX:XLMUSDT",
      "timestamp": "2026-02-15T04:28:46.235176+08:00",
      "has_signal": true,
      "daily": {
        "signals": [
          "三役逆轉"
        ],
        "trend": "趨勢不明確",
        "recommendation": "做空",
        "price": 0.17472,
        "tenkan_sen": 0.163725,
        "kijun_sen": 0.177535,
        "cloud_top": 0.230315,
        "cloud_bottom": 0.225795,
        "senkou_span_a": 0.225795,
        "senkou_span_b": 0.230315
      },
      "h4": {
        "signals": [
          "三役好轉"
        ],
        "trend": "強勢上升趨勢",
        "recommendation": "做多",
        "price": 0.17472,
        "tenkan_sen": 0.167,
        "kijun_sen": 0.163725,
        "cloud_top": 0.1602375,
        "cloud_bottom": 0.159885,
        "senkou_span_a": 0.1602375,
        "senkou_span_b": 0.159885
      },
      "combined_recommendation": "觀望等待",
      "combined_explanation": "逆勢反彈風險高，不建議追多",
      "ai_advice": "根據一目均衡表數據，建議觀望等待，不進行交易。\n- **操作建議**：觀望\n- **進場價位**：無\n- **停損位置**：無\n- **目標價位**：無\n- **風險提醒**：日線和4小時線信號衝突，趨勢不明確，需等待更明確的信號。",
      "ai_provider": "GROQ",
      "ai_model": "llama-3.3-70b-versatile"
    },
    {
      "symbol": "NEAR-USDT",
      "source": "Crypto",
      "chart_url": "https://www.tradingview.com/chart/?symbol=OKX:NEARUSDT",
      "timestamp": "2026-02-15T04:28:46.328371+08:00",
      "has_signal": true,
      "daily": {
        "signals": [
          "三役逆轉",
          "雲層扭轉向上"
        ],
        "trend": "趨勢不明確",
        "recommendation": "觀望",
        "price": 1.089,
        "tenkan_sen": 1.024,
        "kijun_sen": 1.208,
        "cloud_top": 1.6665,
        "cloud_bottom": 1.6524999999999999,
        "senkou_span_a": 1.6665,
        "senkou_span_b": 1.6524999999999999
      },
      "h4": {
        "signals": [
          "三役好轉"
        ],
        "trend": "趨勢不明確",
        "recommendation": "做多",
        "price": 1.089,
        "tenkan_sen": 1.035,
        "kijun_sen": 1.016,
        "cloud_top": 1.04,
        "cloud_bottom": 1.02775,
        "senkou_span_a": 1.02775,
        "senkou_span_b": 1.04
      },
      "combined_recommendation": "短多試單",
      "combined_explanation": "無大趨勢，僅短線多頭機會",
      "ai_advice": "根據一目均衡表數據，提供以下建議：\n1. **操作建議**：做多\n2. **進場價位**：1.0800-1.1000\n3. **停損位置**：1.0200\n4. **目標價位**：1.1500\n5. **風險提醒**：注意雲層範圍的阻力和趨勢不明確的風險。",
      "ai_provider": "GROQ",
      "ai_model": "llama-3.3-70b-versatile"
    },
    {
      "symbol": "APT-USDT",
      "source": "Crypto",
      "chart_url": "https://www.tradingview.com/chart/?symbol=OKX:APTUSDT",
      "timestamp": "2026-02-15T04:28:46.293471+08:00",
      "has_signal": true,
      "daily": {
        "signals": [
          "三役逆轉",
          "雲層扭轉向上"
        ],
        "trend": "趨勢不明確",
        "recommendation": "觀望",
        "price": 0.992,
        "tenkan_sen": 1.0275,
        "kijun_sen": 1.26,
        "cloud_top": 1.76,
        "cloud_bottom": 1.7369999999999999,
        "senkou_span_a": 1.76,
        "senkou_span_b": 1.7369999999999999
      },
      "h4": {
        "signals": [],
        "trend": "趨勢不明確",
        "recommendation": "觀望",
        "price": 0.992,
        "tenkan_sen": 0.9575,
        "kijun_sen": 0.9504999999999999,
        "cloud_top": 1.101,
        "cloud_bottom": 1.0507499999999999,
        "senkou_span_a": 1.0507499999999999,
        "senkou_span_b": 1.101
      },
      "combined_recommendation": "觀望",
      "combined_explanation": "無明確方向，建議等待",
      "ai_advice": "根據一目均衡表數據，APT-USDT的趨勢強度不明確，建議觀望。由於雲層扭轉向上，可能出現反彈機會，但無明確做多或做空信號。\n\n1. **操作建議**：觀望\n2. **進場價位**：無\n3. **停損位置**：0.9500以下\n4. **目標價位**：無\n5. **風險提醒**：注意價格可能繼續下跌，需等待明確的趨勢信號後再進行交易。",
      "ai_provider": "GROQ",
      "ai_model": "llama-3.3-70b-versatile"
    },
    {
      "symbol": "OP-USDT",
      "source": "Crypto",
      "chart_url": "https://www.tradingview.com/chart/?symbol=OKX:OPUSDT",
      "timestamp": "2026-02-15T04:28:46.317374+08:00",
      "has_signal": true,
      "daily": {
        "signals": [
          "三役逆轉"
        ],
        "trend": "趨勢不明確",
        "recommendation": "做空",
        "price": 0.199,
        "tenkan_sen": 0.18805,
        "kijun_sen": 0.242,
        "cloud_top": 0.324075,
        "cloud_bottom": 0.3137,
        "senkou_span_a": 0.324075,
        "senkou_span_b": 0.3137
      },
      "h4": null,
      "combined_recommendation": "做空",
      "combined_explanation": "僅日線資料可用",
      "ai_advice": "根據一目均衡表數據，提供以下建議：\n\n1. **操作建議**：做空\n2. **進場價位**：0.1950 ~ 0.2020\n3. **停損位置**：0.2050\n4. **目標價位**：0.1800\n5. **風險提醒**：注意雲層範圍（0.3137 ~ 0.3241）的阻力和基準線（0.2420）的反彈風險。",
      "ai_provider": "GROQ",
      "ai_model": "llama-3.3-70b-versatile"
    },
    {
      "symbol": "ARB-USDT",
      "source": "Crypto",
      "chart_url": "https://www.tradingview.com/chart/?symbol=OKX:ARBUSDT",
      "timestamp": "2026-02-15T04:28:46.388900+08:00",
      "has_signal": true,
      "daily": {
        "signals": [
          "三役逆轉"
        ],
        "trend": "趨勢不明確",
        "recommendation": "做空",
        "price": 0.1213,
        "tenkan_sen": 0.11524999999999999,
        "kijun_sen": 0.14245,
        "cloud_top": 0.205525,
        "cloud_bottom": 0.2012,
        "senkou_span_a": 0.205525,
        "senkou_span_b": 0.2012
      },
      "h4": {
        "signals": [
          "三役好轉"
        ],
        "trend": "趨勢不明確",
        "recommendation": "做多",
        "price": 0.1213,
        "tenkan_sen": 0.11610000000000001,
        "kijun_sen": 0.1136,
        "cloud_top": 0.11760000000000001,
        "cloud_bottom": 0.11449999999999999,
        "senkou_span_a": 0.11449999999999999,
        "senkou_span_b": 0.11760000000000001
      },
      "combined_recommendation": "觀望等待",
      "combined_explanation": "逆勢反彈風險高，不建議追多",
      "ai_advice": "根據一目均衡表數據，考慮到日線和4小時線的趨勢不明確，建議觀望等待。然而，若要進行操作：\n\n1. **操作建議**：觀望或小資金做多\n2. **進場價位**：0.1161 ~ 0.1180\n3. **停損位置**：0.1120\n4. **目標價位**：0.1250\n5. **風險提醒**：注意雲層範圍和基準線的阻力，風險較高。",
      "ai_provider": "GROQ",
      "ai_model": "llama-3.3-70b-versatile"
    },
    {
      "symbol": "XAUT-USDT",
      "source": "Crypto",
      "chart_url": "https://www.tradingview.com/chart/?symbol=OKX:XAUTUSDT",
      "timestamp": "2026-02-15T04:28:46.590682+08:00",
      "has_signal": false,
      "daily": {
        "signals": [],
        "trend": "趨勢不明確",
        "recommendation": "觀望",
        "price": 4998.3,
        "tenkan_sen": 4985.75,
        "kijun_sen": 5016.799999999999,
        "cloud_top": 4574.5,
        "cloud_bottom": 4455.2,
        "senkou_span_a": 4574.5,
        "senkou_span_b": 4455.2
      },
      "h4": null,
      "combined_recommendation": "觀望",
      "combined_explanation": "僅日線資料可用",
      "ai_advice": null,
      "ai_provider": null,
      "ai_model": null
    },
    {
      "symbol": "PAXG-USDT",
      "source": "Crypto",
      "chart_url": "https://www.tradingview.com/chart/?symbol=OKX:PAXGUSDT",
      "timestamp": "2026-02-15T04:28:46.616531+08:00",
      "has_signal": false,
      "daily": null,
      "h4": null,
      "combined_recommendation": "觀望",
      "combined_explanation": "資料不足",
      "ai_advice": null,
      "ai_provider": null,
      "ai_model": null
    },
    {
      "symbol": "EUR/USD",
      "source": "Forex",
      "chart_url": "https://www.tradingview.com/chart/?symbol=FX:EURUSD",
      "timestamp": "2026-02-15T04:28:47.891441+08:00",
      "has_signal": true,
      "daily": {
        "signals": [
          "轉換線支撐失守"
        ],
        "trend": "趨勢不明確",
        "recommendation": "做空",
        "price": 1.18496,
        "tenkan_sen": 1.18672,
        "kijun_sen": 1.186785,
        "cloud_top": 1.1671999999999998,
        "cloud_bottom": 1.16553,
        "senkou_span_a": 1.1671999999999998,
        "senkou_span_b": 1.16553
      },
      "h4": {
        "signals": [],
        "trend": "盤整區間",
        "recommendation": "觀望",
        "price": 1.18496,
        "tenkan_sen": 1.1865649999999999,
        "kijun_sen": 1.188275,
        "cloud_top": 1.18602,
        "cloud_bottom": 1.18472,
        "senkou_span_a": 1.18602,
        "senkou_span_b": 1.18472
      },
      "combined_recommendation": "偏空操作",
      "combined_explanation": "日線空頭，等待4H確認進場點",
      "ai_advice": "根據一目均衡表數據，提供以下建議：\n\n1. **操作建議**：做空\n2. **進場價位**：1.1850 ~ 1.1868\n3. **停損位置**：1.1900\n4. **目標價位**：1.1655 ~ 1.1672（雲層範圍）\n5. **風險提醒**：注意轉換線和基準線的支撐，避免趨勢逆轉。",
      "ai_provider": "GROQ",
      "ai_model": "llama-3.3-70b-versatile"
    },
    {
      "symbol": "GBP/USD",
      "source": "Forex",
      "chart_url": "https://www.tradingview.com/chart/?symbol=FX:GBPUSD",
      "timestamp": "2026-02-15T04:28:49.112806+08:00",
      "has_signal": true,
      "daily": {
        "signals": [
          "黃金交叉",
          "三役好轉",
          "轉換線支撐失守"
        ],
        "trend": "趨勢不明確",
        "recommendation": "觀望",
        "price": 1.36489,
        "tenkan_sen": 1.36505,
        "kijun_sen": 1.363225,
        "cloud_top": 1.3428200000000001,
        "cloud_bottom": 1.332475,
        "senkou_span_a": 1.3428200000000001,
        "senkou_span_b": 1.332475
      },
      "h4": {
        "signals": [],
        "trend": "趨勢不明確",
        "recommendation": "觀望",
        "price": 1.36489,
        "tenkan_sen": 1.3631799999999998,
        "kijun_sen": 1.36527,
        "cloud_top": 1.3625375,
        "cloud_bottom": 1.36213,
        "senkou_span_a": 1.3625375,
        "senkou_span_b": 1.36213
      },
      "combined_recommendation": "觀望",
      "combined_explanation": "無明確方向，建議等待",
      "ai_advice": "根據一目均衡表數據，操作建議為**觀望**。日線和4小時線均顯示趨勢不明確，轉換線和基準線交叉不明朗。進場價位無明確建議。停損位置參考雲層範圍下緣1.3325。目標價位無明確設置。風險提醒：市場趨勢不明確，建議耐心觀望，等待明確的趨勢信號出現後再進行交易。",
      "ai_provider": "GROQ",
      "ai_model": "llama-3.3-70b-versatile"
    },
    {
      "symbol": "USD/JPY",
      "source": "Forex",
      "chart_url": "https://www.tradingview.com/chart/?symbol=FX:USDJPY",
      "timestamp": "2026-02-15T04:28:50.306781+08:00",
      "has_signal": true,
      "daily": {
        "signals": [
          "三役逆轉"
        ],
        "trend": "趨勢不明確",
        "recommendation": "做空",
        "price": 152.77176,
        "tenkan_sen": 154.794835,
        "kijun_sen": 155.636615,
        "cloud_top": 157.9780725,
        "cloud_bottom": 156.91129999999998,
        "senkou_span_a": 157.9780725,
        "senkou_span_b": 156.91129999999998
      },
      "h4": {
        "signals": [
          "三役逆轉"
        ],
        "trend": "強勢下降趨勢",
        "recommendation": "做空",
        "price": 152.77176,
        "tenkan_sen": 152.99510500000002,
        "kijun_sen": 153.49769,
        "cloud_top": 155.70644,
        "cloud_bottom": 155.59129249999998,
        "senkou_span_a": 155.59129249999998,
        "senkou_span_b": 155.70644
      },
      "combined_recommendation": "強力做空",
      "combined_explanation": "日線與4H共振空頭，高勝率機會",
      "ai_advice": "根據一目均衡表數據，**操作建議**：做空。\n**進場價位**：152.5 ~ 153.0。\n**停損位置**：155.5，基於雲層範圍的上緣。\n**目標價位**：150.0，考慮趨勢下降趨勢。\n**風險提醒**：注意趨勢不明確的日線判斷，交易需謹慎。",
      "ai_provider": "GROQ",
      "ai_model": "llama-3.3-70b-versatile"
    },
    {
      "symbol": "AUD/USD",
      "source": "Forex",
      "chart_url": "https://www.tradingview.com/chart/?symbol=FX:AUDUSD",
      "timestamp": "2026-02-15T04:28:51.479457+08:00",
      "has_signal": true,
      "daily": {
        "signals": [
          "三役好轉"
        ],
        "trend": "強勢上升趨勢",
        "recommendation": "做多",
        "price": 0.70732,
        "tenkan_sen": 0.7071000000000001,
        "kijun_sen": 0.693705,
        "cloud_top": 0.67089,
        "cloud_bottom": 0.660245,
        "senkou_span_a": 0.67089,
        "senkou_span_b": 0.660245
      },
      "h4": {
        "signals": [],
        "trend": "趨勢不明確",
        "recommendation": "觀望",
        "price": 0.70732,
        "tenkan_sen": 0.7066250000000001,
        "kijun_sen": 0.70957,
        "cloud_top": 0.7028160975,
        "cloud_bottom": 0.699835,
        "senkou_span_a": 0.7028160975,
        "senkou_span_b": 0.699835
      },
      "combined_recommendation": "偏多操作",
      "combined_explanation": "日線多頭，等待4H確認進場點",
      "ai_advice": "根據一目均衡表數據，提供以下建議：\n\n1. **操作建議**：做多\n2. **進場價位**：0.7050 ~ 0.7080\n3. **停損位置**：0.6937\n4. **目標價位**：0.7200\n5. **風險提醒**：注意日線和4小時線的趨勢差異，謹慎管理風險。",
      "ai_provider": "GROQ",
      "ai_model": "llama-3.3-70b-versatile"
    },
    {
      "symbol": "USD/CHF",
      "source": "Forex",
      "chart_url": "https://www.tradingview.com/chart/?symbol=FX:USDCHF",
      "timestamp": "2026-02-15T04:29:52.665718+08:00",
      "has_signal": true,
      "daily": {
        "signals": [
          "三役逆轉"
        ],
        "trend": "強勢下降趨勢",
        "recommendation": "做空",
        "price": 0.76883,
        "tenkan_sen": 0.769835,
        "kijun_sen": 0.77874,
        "cloud_top": 0.798235,
        "cloud_bottom": 0.7955350000000001,
        "senkou_span_a": 0.7955350000000001,
        "senkou_span_b": 0.798235
      },
      "h4": {
        "signals": [
          "死亡交叉",
          "基準線阻力回落"
        ],
        "trend": "趨勢不明確",
        "recommendation": "做空",
        "price": 0.76883,
        "tenkan_sen": 0.7687999999999999,
        "kijun_sen": 0.76898,
        "cloud_top": 0.772385,
        "cloud_bottom": 0.770237505,
        "senkou_span_a": 0.770237505,
        "senkou_span_b": 0.772385
      },
      "combined_recommendation": "強力做空",
      "combined_explanation": "日線與4H共振空頭，高勝率機會",
      "ai_advice": "根據一目均衡表數據，提供以下建議：\n\n1. **操作建議**：做空\n2. **進場價位**：0.7700 ~ 0.7720\n3. **停損位置**：0.7787（基準線）\n4. **目標價位**：0.7600\n5. **風險提醒**：注意雲層範圍（0.7955 ~ 0.7982）反彈風險，趨勢不明確時應謹慎交易。",
      "ai_provider": "GROQ",
      "ai_model": "llama-3.3-70b-versatile"
    },
    {
      "symbol": "USD/CAD",
      "source": "Forex",
      "chart_url": "https://www.tradingview.com/chart/?symbol=FX:USDCAD",
      "timestamp": "2026-02-15T04:29:53.857702+08:00",
      "has_signal": true,
      "daily": {
        "signals": [
          "三役逆轉"
        ],
        "trend": "趨勢不明確",
        "recommendation": "做空",
        "price": 1.36194,
        "tenkan_sen": 1.359385,
        "kijun_sen": 1.36636,
        "cloud_top": 1.388425,
        "cloud_bottom": 1.3829325,
        "senkou_span_a": 1.3829325,
        "senkou_span_b": 1.388425
      },
      "h4": {
        "signals": [],
        "trend": "盤整區間",
        "recommendation": "觀望",
        "price": 1.36194,
        "tenkan_sen": 1.361575,
        "kijun_sen": 1.35712,
        "cloud_top": 1.362435,
        "cloud_bottom": 1.3609175,
        "senkou_span_a": 1.3609175,
        "senkou_span_b": 1.362435
      },
      "combined_recommendation": "偏空操作",
      "combined_explanation": "日線空頭，等待4H確認進場點",
      "ai_advice": "根據一目均衡表數據，提供以下建議：\n\n1. **操作建議**：做空\n2. **進場價位**：1.3620 ~ 1.3640\n3. **停損位置**：1.3680\n4. **目標價位**：1.3550\n5. **風險提醒**：雲層範圍（1.3829 ~ 1.3884）可能形成強力阻力，應注意趨勢逆轉風險。",
      "ai_provider": "GROQ",
      "ai_model": "llama-3.3-70b-versatile"
    },
    {
      "symbol": "NZD/USD",
      "source": "Forex",
      "chart_url": "https://www.tradingview.com/chart/?symbol=FX:NZDUSD",
      "timestamp": "2026-02-15T04:29:55.045034+08:00",
      "has_signal": true,
      "daily": {
        "signals": [
          "三役好轉",
          "轉換線支撐失守"
        ],
        "trend": "趨勢不明確",
        "recommendation": "觀望",
        "price": 0.60374,
        "tenkan_sen": 0.60379099,
        "kijun_sen": 0.59573,
        "cloud_top": 0.57837,
        "cloud_bottom": 0.57219,
        "senkou_span_a": 0.57837,
        "senkou_span_b": 0.57219
      },
      "h4": {
        "signals": [],
        "trend": "趨勢不明確",
        "recommendation": "觀望",
        "price": 0.60374,
        "tenkan_sen": 0.603405,
        "kijun_sen": 0.604595,
        "cloud_top": 0.602157995,
        "cloud_bottom": 0.5996,
        "senkou_span_a": 0.602157995,
        "senkou_span_b": 0.5996
      },
      "combined_recommendation": "觀望",
      "combined_explanation": "無明確方向，建議等待",
      "ai_advice": "根據一目均衡表數據，NZD/USD 屬於觀望狀態。由於趨勢不明確，建議暫時觀望。\n\n- **操作建議**：觀望\n- **進場價位**：無\n- **停損位置**：無\n- **目標價位**：無\n- **風險提醒**：注意雲層範圍（0.5722 ~ 0.5784）和轉換線（0.6038）的支撐和阻力，並關注日線和4小時線的趨勢變化。",
      "ai_provider": "GROQ",
      "ai_model": "llama-3.3-70b-versatile"
    },
    {
      "symbol": "XAU/USD",
      "source": "Forex",
      "chart_url": "https://www.tradingview.com/chart/?symbol=FX:XAUUSD",
      "timestamp": "2026-02-15T04:29:56.239196+08:00",
      "has_signal": false,
      "daily": {
        "signals": [],
        "trend": "趨勢不明確",
        "recommendation": "觀望",
        "price": 5043.18973,
        "tenkan_sen": 5003.517215,
        "kijun_sen": 5004.03759,
        "cloud_top": 4580.798269999999,
        "cloud_bottom": 4467.3773,
        "senkou_span_a": 4580.798269999999,
        "senkou_span_b": 4467.3773
      },
      "h4": {
        "signals": [],
        "trend": "趨勢不明確",
        "recommendation": "觀望",
        "price": 5043.18973,
        "tenkan_sen": 4998.8214100000005,
        "kijun_sen": 5003.517215,
        "cloud_top": 5001.001018999999,
        "cloud_bottom": 4752.30314,
        "senkou_span_a": 5001.001018999999,
        "senkou_span_b": 4752.30314
      },
      "combined_recommendation": "觀望",
      "combined_explanation": "無明確方向，建議等待",
      "ai_advice": null,
      "ai_provider": null,
      "ai_model": null
    }
  ]
}